MANIFEST.in
README.txt
requirements.txt
setup.py
bcbreport/__init__.py
bcbreport/header.Rmd
bcbreport/prepare.py
bcbreport/qc.Rmd
bcbreport/qsignature.Rmd
bcbreport/regions.Rmd
bcbreport/report.Rmd
bcbreport/variants.Rmd
bcbreport.egg-info/PKG-INFO
bcbreport.egg-info/SOURCES.txt
bcbreport.egg-info/dependency_links.txt
bcbreport.egg-info/not-zip-safe
bcbreport.egg-info/top_level.txt